{
    "efficiency_metrics": [
        {
            "task": "\n        Analyze the system description. \n        Populate the 'architectural_approaches' section of the MASTER DATA SCHEMA.\n        Ensure you use the exact keys: 'approach_name', 'description', 'addressed_attributes'.\n        ",
            "details": [
                {
                    "agent_name": "Architect",
                    "input_tokens": 2277,
                    "output_tokens": 49,
                    "time_taken": 9.91
                },
                {
                    "agent_name": "Customer",
                    "input_tokens": 2844,
                    "output_tokens": 369,
                    "time_taken": 6.88
                },
                {
                    "agent_name": "Architect",
                    "input_tokens": 2690,
                    "output_tokens": 78,
                    "time_taken": 2.52
                },
                {
                    "agent_name": "Customer",
                    "input_tokens": 2873,
                    "output_tokens": 1191,
                    "time_taken": 21.42
                },
                {
                    "agent_name": "Architect",
                    "input_tokens": 4112,
                    "output_tokens": 584,
                    "time_taken": 22.58
                }
            ]
        },
        {
            "task": "\n        Generate the 'utility_tree' sections based on the MASTER DATA SCHEMA.\n        Ensure 'utility_tree' follows the root -> quality_attribute_nodes -> children structure.\n        Consult the Architect for technical review before finalizing.\n        ",
            "details": [
                {
                    "agent_name": "Manager",
                    "input_tokens": 2603,
                    "output_tokens": 106,
                    "time_taken": 9.52
                },
                {
                    "agent_name": "Architect",
                    "input_tokens": 2667,
                    "output_tokens": 58,
                    "time_taken": 8.23
                },
                {
                    "agent_name": "Manager",
                    "input_tokens": 2674,
                    "output_tokens": 76,
                    "time_taken": 1.67
                },
                {
                    "agent_name": "Architect",
                    "input_tokens": 2636,
                    "output_tokens": 59,
                    "time_taken": 3.08
                },
                {
                    "agent_name": "Manager",
                    "input_tokens": 2746,
                    "output_tokens": 59,
                    "time_taken": 2.34
                },
                {
                    "agent_name": "Customer",
                    "input_tokens": 2854,
                    "output_tokens": 483,
                    "time_taken": 8.1
                },
                {
                    "agent_name": "Manager",
                    "input_tokens": 3336,
                    "output_tokens": 70,
                    "time_taken": 1.69
                },
                {
                    "agent_name": "Architect",
                    "input_tokens": 2630,
                    "output_tokens": 50,
                    "time_taken": 1.32
                },
                {
                    "agent_name": "Manager",
                    "input_tokens": 3436,
                    "output_tokens": 1006,
                    "time_taken": 21.56
                }
            ]
        },
        {
            "task": "\n        Generate scenarios and populate the 'scenarios' section of the MASTER DATA SCHEMA.\n        Ensure each scenario strictly follows the 'scenario_id', 'scenario_text', and 'related_quality_attributes' keys.\n        ",
            "details": [
                {
                    "agent_name": "Manager",
                    "input_tokens": 4534,
                    "output_tokens": 607,
                    "time_taken": 10.55
                }
            ]
        },
        {
            "task": "\n        Perform analysis. Populate the 'analysis_records' section of the MASTER DATA SCHEMA.\n        Ensure findings include 'risks', 'non_risks', 'sensitivity_points', and 'tradeoff_points' strictly following the schema.\n        ",
            "details": [
                {
                    "agent_name": "EvaluationTeam",
                    "input_tokens": 3715,
                    "output_tokens": 143,
                    "time_taken": 3.36
                },
                {
                    "agent_name": "Architect",
                    "input_tokens": 2705,
                    "output_tokens": 134,
                    "time_taken": 2.5
                },
                {
                    "agent_name": "EvaluationTeam",
                    "input_tokens": 3863,
                    "output_tokens": 61,
                    "time_taken": 2.02
                },
                {
                    "agent_name": "Architect",
                    "input_tokens": 2621,
                    "output_tokens": 98,
                    "time_taken": 1.81
                },
                {
                    "agent_name": "EvaluationTeam",
                    "input_tokens": 3975,
                    "output_tokens": 197,
                    "time_taken": 4.7
                },
                {
                    "agent_name": "Architect",
                    "input_tokens": 2759,
                    "output_tokens": 146,
                    "time_taken": 3.0
                },
                {
                    "agent_name": "EvaluationTeam",
                    "input_tokens": 4138,
                    "output_tokens": 99,
                    "time_taken": 2.05
                },
                {
                    "agent_name": "Architect",
                    "input_tokens": 2661,
                    "output_tokens": 135,
                    "time_taken": 3.16
                },
                {
                    "agent_name": "EvaluationTeam",
                    "input_tokens": 4324,
                    "output_tokens": 3993,
                    "time_taken": 104.17
                }
            ]
        }
    ]
}